{"trial_id": "2df262bb03e08bca7ffdf545ca64e890", "hyperparameters": {"space": [{"class_name": "Boolean", "config": {"name": "structured_data_block_1/normalize", "default": false, "conditions": []}}, {"class_name": "Boolean", "config": {"name": "structured_data_block_1/dense_block_1/use_batchnorm", "default": false, "conditions": []}}, {"class_name": "Choice", "config": {"name": "structured_data_block_1/dense_block_1/num_layers", "default": 2, "conditions": [], "values": [1, 2, 3], "ordered": true}}, {"class_name": "Choice", "config": {"name": "structured_data_block_1/dense_block_1/units_0", "default": 32, "conditions": [], "values": [16, 32, 64, 128, 256, 512, 1024], "ordered": true}}, {"class_name": "Choice", "config": {"name": "structured_data_block_1/dense_block_1/dropout", "default": 0.0, "conditions": [], "values": [0.0, 0.25, 0.5], "ordered": true}}, {"class_name": "Choice", "config": {"name": "structured_data_block_1/dense_block_1/units_1", "default": 32, "conditions": [], "values": [16, 32, 64, 128, 256, 512, 1024], "ordered": true}}, {"class_name": "Choice", "config": {"name": "regression_head_1/dropout", "default": 0, "conditions": [], "values": [0.0, 0.25, 0.5], "ordered": true}}, {"class_name": "Choice", "config": {"name": "optimizer", "default": "adam", "conditions": [], "values": ["adam", "sgd", "adam_weight_decay"], "ordered": false}}, {"class_name": "Choice", "config": {"name": "learning_rate", "default": 0.001, "conditions": [], "values": [0.1, 0.01, 0.001, 0.0001, 2e-05, 1e-05], "ordered": true}}], "values": {"structured_data_block_1/normalize": true, "structured_data_block_1/dense_block_1/use_batchnorm": false, "structured_data_block_1/dense_block_1/num_layers": 2, "structured_data_block_1/dense_block_1/units_0": 32, "structured_data_block_1/dense_block_1/dropout": 0.5, "structured_data_block_1/dense_block_1/units_1": 32, "regression_head_1/dropout": 0.0, "optimizer": "adam", "learning_rate": 0.001}}, "metrics": {"metrics": {"loss": {"direction": "min", "observations": [{"value": [2.2838268280029297], "step": 0}, {"value": [1.4157311916351318], "step": 1}, {"value": [1.1173053979873657], "step": 2}, {"value": [1.0024338960647583], "step": 3}, {"value": [0.8919795751571655], "step": 4}, {"value": [0.8057306408882141], "step": 5}, {"value": [0.8298996686935425], "step": 6}, {"value": [0.7700416445732117], "step": 7}, {"value": [0.7428274154663086], "step": 8}, {"value": [0.7171324491500854], "step": 9}]}, "mean_squared_error": {"direction": "min", "observations": [{"value": [2.2838268280029297], "step": 0}, {"value": [1.4157311916351318], "step": 1}, {"value": [1.1173053979873657], "step": 2}, {"value": [1.0024338960647583], "step": 3}, {"value": [0.8919795751571655], "step": 4}, {"value": [0.8057306408882141], "step": 5}, {"value": [0.8298996686935425], "step": 6}, {"value": [0.7700416445732117], "step": 7}, {"value": [0.7428274154663086], "step": 8}, {"value": [0.7171324491500854], "step": 9}]}, "val_loss": {"direction": "min", "observations": [{"value": [2.5253899097442627], "step": 0}, {"value": [2.1545236110687256], "step": 1}, {"value": [1.842519760131836], "step": 2}, {"value": [1.6928919553756714], "step": 3}, {"value": [1.6169984340667725], "step": 4}, {"value": [1.4541685581207275], "step": 5}, {"value": [1.4243828058242798], "step": 6}, {"value": [1.3719004392623901], "step": 7}, {"value": [1.3576455116271973], "step": 8}, {"value": [1.3358665704727173], "step": 9}]}, "val_mean_squared_error": {"direction": "min", "observations": [{"value": [2.5253899097442627], "step": 0}, {"value": [2.1545236110687256], "step": 1}, {"value": [1.842519760131836], "step": 2}, {"value": [1.6928919553756714], "step": 3}, {"value": [1.6169984340667725], "step": 4}, {"value": [1.4541685581207275], "step": 5}, {"value": [1.4243828058242798], "step": 6}, {"value": [1.3719004392623901], "step": 7}, {"value": [1.3576455116271973], "step": 8}, {"value": [1.3358665704727173], "step": 9}]}}}, "score": 1.3358665704727173, "best_step": 9, "status": "COMPLETED"}